datatransfer/__init__.py
datatransfer-0.0.3.dist-info/METADATA
datatransfer-0.0.3.dist-info/WHEEL
datatransfer-0.0.3.dist-info/entry_points.txt
datatransfer-0.0.3.dist-info/top_level.txt
datatransfer-0.0.3.dist-info/RECORD
