Metadata-Version: 2.1
Name: datatransfer
Version: 0.0.3
Summary: 此模块用于把excel表处理成规范的.xlsx导入模板
Home-page: UNKNOWN
Author: Lee
Author-email: me@liyuebin.cn
License: UNKNOWN
Platform: UNKNOWN
